[
    {
        "key": "dbln",
        "value": "%7B%2261550758168638%22%3A%22PdBIwLGI%22%7D",
        "domain": "facebook.com",
        "path": "/login/device-based/",
        "hostOnly": false,
        "creation": "2024-07-28T01:28:54.614Z",
        "lastAccessed": "2024-07-28T01:28:54.615Z"
    },
    {
        "key": "datr",
        "value": "h-yNZuF-5h1J5OX4GCrMjNiy",
        "domain": "facebook.com",
        "path": "/",
        "hostOnly": false,
        "creation": "2024-07-28T01:28:54.615Z",
        "lastAccessed": "2024-07-28T01:28:54.615Z"
    },
    {
        "key": "sb",
        "value": "h-yNZsWFBDTPw9mxsgGLWxbr",
        "domain": "facebook.com",
        "path": "/",
        "hostOnly": false,
        "creation": "2024-07-28T01:28:54.615Z",
        "lastAccessed": "2024-07-28T01:28:54.615Z"
    },
    {
        "key": "fr",
        "value": "0QFtn3DWUXgPz1jgj.AWUeZ7LwVISvog-R7SBSk9Dujf0.BmjeyH..AAA.0.0.Bmje0N.AWXrhLJjH80",
        "domain": "facebook.com",
        "path": "/",
        "hostOnly": false,
        "creation": "2024-07-28T01:28:54.615Z",
        "lastAccessed": "2024-07-28T01:28:54.615Z"
    },
    {
        "key": "c_user",
        "value": "61550758168638",
        "domain": "facebook.com",
        "path": "/",
        "hostOnly": false,
        "creation": "2024-07-28T01:28:54.615Z",
        "lastAccessed": "2024-07-28T01:28:54.615Z"
    },
    {
        "key": "xs",
        "value": "37%3Aupm4oGXdHHDrdA%3A2%3A1720577297%3A-1%3A16335",
        "domain": "facebook.com",
        "path": "/",
        "hostOnly": false,
        "creation": "2024-07-28T01:28:54.615Z",
        "lastAccessed": "2024-07-28T01:28:54.615Z"
    },
    {
        "key": "m_page_voice",
        "value": "61550758168638",
        "domain": "facebook.com",
        "path": "/",
        "hostOnly": false,
        "creation": "2024-07-28T01:28:54.615Z",
        "lastAccessed": "2024-07-28T01:28:54.615Z"
    },
    {
        "key": "ps_n",
        "value": "1",
        "domain": "facebook.com",
        "path": "/",
        "hostOnly": false,
        "creation": "2024-07-28T01:28:54.615Z",
        "lastAccessed": "2024-07-28T01:28:54.615Z"
    },
    {
        "key": "ps_l",
        "value": "1",
        "domain": "facebook.com",
        "path": "/",
        "hostOnly": false,
        "creation": "2024-07-28T01:28:54.615Z",
        "lastAccessed": "2024-07-28T01:28:54.615Z"
    },
    {
        "key": "locale",
        "value": "vi_VN",
        "domain": "facebook.com",
        "path": "/",
        "hostOnly": false,
        "creation": "2024-07-28T01:28:54.615Z",
        "lastAccessed": "2024-07-28T01:28:54.615Z"
    },
    {
        "key": "dpr",
        "value": "2.802304267883301",
        "domain": "facebook.com",
        "path": "/",
        "hostOnly": false,
        "creation": "2024-07-28T01:28:54.615Z",
        "lastAccessed": "2024-07-28T01:28:54.615Z"
    },
    {
        "key": "fbl_st",
        "value": "101639503%3BT%3A28701050",
        "domain": "facebook.com",
        "path": "/",
        "hostOnly": false,
        "creation": "2024-07-28T01:28:54.615Z",
        "lastAccessed": "2024-07-28T01:28:54.615Z"
    },
    {
        "key": "vpd",
        "value": "v1%3B514x313x2.3014395236968994",
        "domain": "facebook.com",
        "path": "/",
        "hostOnly": false,
        "creation": "2024-07-28T01:28:54.615Z",
        "lastAccessed": "2024-07-28T01:28:54.615Z"
    },
    {
        "key": "wl_cbv",
        "value": "v2%3Bclient_version%3A2573%3Btimestamp%3A1722063053",
        "domain": "facebook.com",
        "path": "/",
        "hostOnly": false,
        "creation": "2024-07-28T01:28:54.615Z",
        "lastAccessed": "2024-07-28T01:28:54.615Z"
    }
	    ]
